machine_stats/__init__.py
machine_stats/__main__.py
machine_stats/_version.py
machine_stats/config.py
machine_stats/modules/cpu_utilization.py
machine_stats/modules/proc_stats.py
machine_stats/plugins/cpu_utilization.py
machine_stats/plugins/proc_stats.py
machine_stats-3.0.2.dist-info/METADATA
machine_stats-3.0.2.dist-info/WHEEL
machine_stats-3.0.2.dist-info/entry_points.txt
machine_stats-3.0.2.dist-info/RECORD
