Metadata-Version: 2.4
Name: machine_stats
Version: 3.0.2
Summary: A simple and effective way to gather machine statistics (RAM, Storage, CPU, etc.) from server environment
Classifier: Intended Audience :: System Administrators
Classifier: License :: OSI Approved :: MIT License
Classifier: Operating System :: POSIX :: Linux
Classifier: Operating System :: Unix
Classifier: Programming Language :: Python :: 3
Classifier: Programming Language :: Python :: 3.10
Classifier: Programming Language :: Python :: 3.11
Classifier: Programming Language :: Python :: 3.12
Classifier: Programming Language :: Python :: 3.13
Classifier: Programming Language :: Python :: 3.14
Classifier: Topic :: System :: Monitoring
Classifier: Topic :: System :: Systems Administration
Requires-Python: <=3.14,>=3.10
Requires-Dist: ansible-core>=2.12
Requires-Dist: ansible-runner==2.4.2
Requires-Dist: pluginbase
